ocean/__init__.py
ocean/api.py
ocean/code.py
ocean/main.py
ocean/utils.py
ocean/commands/__init__.py
ocean/commands/cmd_create.py
ocean/commands/cmd_data.py
ocean/commands/cmd_delete.py
ocean/commands/cmd_get.py
ocean/commands/cmd_init.py
ocean/commands/cmd_login.py
ocean/commands/cmd_logout.py
ocean/commands/cmd_logs.py
ocean/commands/cmd_set.py
ocean/commands/cmd_version.py
ocean_cli-0.2.3.dist-info/METADATA
ocean_cli-0.2.3.dist-info/WHEEL
ocean_cli-0.2.3.dist-info/entry_points.txt
ocean_cli-0.2.3.dist-info/top_level.txt
ocean_cli-0.2.3.dist-info/RECORD
