Metadata-Version: 2.1
Name: ocean-cli
Version: 0.2.3
Summary: Ocean CLI
Home-page: https://github.com/AI-Ocean/ocean-cli
Author: kairos03
Author-email: kairos0=9603@email.com
License: UNKNOWN
Platform: UNKNOWN
Classifier: Programming Language :: Python :: 3
Classifier: Programming Language :: Python :: 3.6
Classifier: Programming Language :: Python :: 3.7
Classifier: Programming Language :: Python :: 3.8
Classifier: Programming Language :: Python :: 3.9
Classifier: Environment :: Console
Classifier: Operating System :: OS Independent
Requires-Python: >=3.6
Requires-Dist: click (~=8.0.1)
Requires-Dist: python-dateutil
Requires-Dist: requests (~=2.26.0)
Requires-Dist: inquirer
Requires-Dist: pyyaml
Requires-Dist: sentry-sdk
